telecomcredit/__init__.py
telecomcredit/_base.py
telecomcredit/_client.py
telecomcredit/_credit_card.py
telecomcredit/_webhook.py
telecomcredit-1.0.4.dist-info/LICENSE
telecomcredit-1.0.4.dist-info/METADATA
telecomcredit-1.0.4.dist-info/WHEEL
telecomcredit-1.0.4.dist-info/top_level.txt
telecomcredit-1.0.4.dist-info/RECORD
